{
  "gameData": {
    "teams": {
      "away": {
        "id": 134,
        "name": "Pacific City Pilots",
        "abbreviation": "PCP",
        "teamName": "Pilots"
      },
      "home": {
        "id": 133,
        "name": "Bay Area Bombers",
        "abbreviation": "BAY",
        "teamName": "Bombers"
      }
    }
  },
  "plays": [
    {
      "result": {
        "type": "atBat",
        "event": "Lineout",
        "eventType": "field_out",
        "description": "",
        "rbi": 0,
        "awayScore": 0,
        "homeScore": 0
      },
      "about": {
        "atBatIndex": 0,
        "halfInning": "top",
        "isTopInning": true,
        "inning": 1,
        "isScoringPlay": false
      },
      "count": {
        "balls": 0,
        "strikes": 0,
        "outs": 1
      },
      "matchup": {
        "batter": {
          "id": 625201,
          "fullName": "Alex Chase",
          "link": "/api/v1/people/625201"
        },
        "batSide": {
          "code": "R",
          "description": "Right"
        },
        "pitcher": {
          "id": 605110,
          "fullName": "Joe Gibson",
          "link": "/api/v1/people/605110"
        },
        "pitchHand": {
          "code": "R",
          "description": "Right"
        },
        "splits": {
          "batter": "vs_RHP",
          "pitcher": "vs_RHB",
          "menOnBase": "Empty"
        }
      },
      "playEvents": [
        {
          "index": 0,
          "count": {
            "balls": 0,
            "strikes": 0
          },
          "details": {
            "code": "F",
            "description": "Foul",
            "isStrike": true,
            "type": {
              "code": "SL",
              "description": "Slider"
            }
          },
          "pitchData": {
            "startSpeed": 89.0,
            "breaks": {
              "spinRate": 2670
            }
          }
        },
        {
          "index": 1,
          "count": {
            "balls": 0,
            "strikes": 1
          },
          "details": {
            "code": "B",
            "description": "Ball",
            "isStrike": false,
            "type": {
              "code": "FF",
              "description": "Four-seam fastball"
            }
          },
          "pitchData": {
            "startSpeed": 94.2,
            "breaks": {
              "spinRate": 2249
            }
          }
        },
        {
          "index": 2,
          "count": {
            "balls": 1,
            "strikes": 1
          },
          "details": {
            "code": "C",
            "description": "Called Strike",
            "isStrike": true,
            "type": {
              "code": "SL",
              "description": "Slider"
            }
          },
          "pitchData": {
            "startSpeed": 87.8,
            "breaks": {
              "spinRate": 2627
            }
          }
        },
        {
          "index": 3,
          "count": {
            "balls": 1,
            "strikes": 2
          },
          "details": {
            "code": "X",
            "description": "In play, Lineout",
            "isStrike": true,
            "type": {
              "code": "FF",
              "description": "Four-seam fastball"
            }
          },
          "pitchData": {
            "startSpeed": 95.3,
            "breaks": {
              "spinRate": 2432
            }
          },
          "hitData": {
            "launchSpeed": 82.4,
            "launchAngle": 15.1,
            "trajectory": "line_drive"
          }
        }
      ],
      "runners": [
        {
          "movement": {
            "originBase": null,
            "start": null,
            "end": null,
            "outBase": "1B",
            "isOut": true,
            "outNumber": 1
          },
          "details": {
            "event": "Lineout",
            "eventType": "field_out",
            "movementReason": null,
            "runner": {
              "id": 625201,
              "fullName": "Alex Chase",
              "link": "/api/v1/people/625201"
            },
            "isScoringEvent": false,
            "rbi": false,
            "earned": false,
            "teamUnearned": false,
            "playIndex": 3
          },
          "credits": [
            {
              "player": {
                "id": 545106
              },
              "position": {
                "code": "4",
                "name": "Second Base",
                "abbreviation": "2B"
              },
              "credit": "putout"
            }
          ]
        }
      ]
    },
    {
      "result": {
        "type": "atBat",
        "event": "Home Run",
        "eventType": "home_run",
        "description": "",
        "rbi": 1,
        "awayScore": 1,
        "homeScore": 0
      },
      "about": {
        "atBatIndex": 16,
        "halfInning": "top",
        "isTopInning": true,
        "inning": 3,
        "isScoringPlay": true
      },
      "count": {
        "balls": 0,
        "strikes": 0,
        "outs": 1
      },
      "matchup": {
        "batter": {
          "id": 625209,
          "fullName": "TJ Hawkins",
          "link": "/api/v1/people/625209"
        },
        "batSide": {
          "code": "R",
          "description": "Right"
        },
        "pitcher": {
          "id": 605110,
          "fullName": "Joe Gibson",
          "link": "/api/v1/people/605110"
        },
        "pitchHand": {
          "code": "R",
          "description": "Right"
        },
        "splits": {
          "batter": "vs_RHP",
          "pitcher": "vs_RHB",
          "menOnBase": "Empty"
        }
      },
      "playEvents": [
        {
          "index": 59,
          "count": {
            "balls": 0,
            "strikes": 0
          },
          "details": {
            "code": "F",
            "description": "Foul",
            "isStrike": true,
            "type": {
              "code": "CU",
              "description": "Curveball"
            }
          },
          "pitchData": {
            "startSpeed": 79.2,
            "breaks": {
              "spinRate": 2884
            }
          }
        },
        {
          "index": 60,
          "count": {
            "balls": 0,
            "strikes": 1
          },
          "details": {
            "code": "C",
            "description": "Called Strike",
            "isStrike": true,
            "type": {
              "code": "CH",
              "description": "Changeup"
            }
          },
          "pitchData": {
            "startSpeed": 82.5,
            "breaks": {
              "spinRate": 1723
            }
          }
        },
        {
          "index": 61,
          "count": {
            "balls": 0,
            "strikes": 2
          },
          "details": {
            "code": "X",
            "description": "In play, Home Run",
            "isStrike": true,
            "type": {
              "code": "FF",
              "description": "Four-seam fastball"
            }
          },
          "pitchData": {
            "startSpeed": 96.0,
            "breaks": {
              "spinRate": 2331
            }
          },
          "hitData": {
            "launchSpeed": 113.6,
            "launchAngle": 28.5,
            "trajectory": "fly_ball"
          }
        }
      ],
      "runners": [
        {
          "movement": {
            "originBase": null,
            "start": null,
            "end": "score",
            "outBase": null,
            "isOut": false,
            "outNumber": null
          },
          "details": {
            "event": "Home Run",
            "eventType": "home_run",
            "movementReason": null,
            "runner": {
              "id": 625209,
              "fullName": "TJ Hawkins",
              "link": "/api/v1/people/625209"
            },
            "isScoringEvent": true,
            "rbi": true,
            "earned": true,
            "teamUnearned": false,
            "playIndex": 2,
            "responsiblePitcher": {
              "id": 605110,
              "link": "/api/v1/people/605110"
            }
          },
          "credits": []
        }
      ]
    },
    {
      "result": {
        "type": "atBat",
        "event": "Groundout",
        "eventType": "field_out",
        "description": "",
        "rbi": 0,
        "awayScore": 0,
        "homeScore": 0
      },
      "about": {
        "atBatIndex": 1,
        "halfInning": "top",
        "isTopInning": true,
        "inning": 1,
        "isScoringPlay": false
      },
      "count": {
        "balls": 0,
        "strikes": 0,
        "outs": 2
      },
      "matchup": {
        "batter": {
          "id": 625202,
          "fullName": "Kevin Webb",
          "link": "/api/v1/people/625202"
        },
        "batSide": {
          "code": "L",
          "description": "Left"
        },
        "pitcher": {
          "id": 605110,
          "fullName": "Joe Gibson",
          "link": "/api/v1/people/605110"
        },
        "pitchHand": {
          "code": "R",
          "description": "Right"
        },
        "splits": {
          "batter": "vs_RHP",
          "pitcher": "vs_LHB",
          "menOnBase": "Empty"
        }
      },
      "playEvents": [
        {
          "index": 4,
          "count": {
            "balls": 0,
            "strikes": 0
          },
          "details": {
            "code": "C",
            "description": "Called Strike",
            "isStrike": true,
            "type": {
              "code": "CH",
              "description": "Changeup"
            }
          },
          "pitchData": {
            "startSpeed": 82.2,
            "breaks": {
              "spinRate": 1664
            }
          }
        },
        {
          "index": 5,
          "count": {
            "balls": 0,
            "strikes": 1
          },
          "details": {
            "code": "X",
            "description": "In play, Groundout",
            "isStrike": true,
            "type": {
              "code": "CH",
              "description": "Changeup"
            }
          },
          "pitchData": {
            "startSpeed": 82.6,
            "breaks": {
              "spinRate": 1874
            }
          },
          "hitData": {
            "launchSpeed": 92.6,
            "launchAngle": -5.9,
            "trajectory": "ground_ball"
          }
        }
      ],
      "runners": [
        {
          "movement": {
            "originBase": null,
            "start": null,
            "end": null,
            "outBase": "1B",
            "isOut": true,
            "outNumber": 2
          },
          "details": {
            "event": "Groundout",
            "eventType": "field_out",
            "movementReason": null,
            "runner": {
              "id": 625202,
              "fullName": "Kevin Webb",
              "link": "/api/v1/people/625202"
            },
            "isScoringEvent": false,
            "rbi": false,
            "earned": false,
            "teamUnearned": false,
            "playIndex": 1
          },
          "credits": [
            {
              "player": {
                "id": 545106
              },
              "credit": "assist"
            },
            {
              "player": {
                "id": 545107
              },
              "credit": "putout"
            }
          ]
        }
      ]
    },
    {
      "result": {
        "type": "atBat",
        "event": "Flyout",
        "eventType": "field_out",
        "description": "",
        "rbi": 0,
        "awayScore": 0,
        "homeScore": 0
      },
      "about": {
        "atBatIndex": 4,
        "halfInning": "bottom",
        "isTopInning": false,
        "inning": 1,
        "isScoringPlay": false
      },
      "count": {
        "balls": 0,
        "strikes": 0,
        "outs": 2
      },
      "matchup": {
        "batter": {
          "id": 545102,
          "fullName": "Marcus Thorne",
          "link": "/api/v1/people/545102"
        },
        "batSide": {
          "code": "L",
          "description": "Left"
        },
        "pitcher": {
          "id": 645210,
          "fullName": "Miguel Garcia",
          "link": "/api/v1/people/645210"
        },
        "pitchHand": {
          "code": "L",
          "description": "Left"
        },
        "splits": {
          "batter": "vs_LHP",
          "pitcher": "vs_LHB",
          "menOnBase": "Empty"
        }
      },
      "playEvents": [
        {
          "index": 11,
          "count": {
            "balls": 0,
            "strikes": 0
          },
          "details": {
            "code": "B",
            "description": "Ball",
            "isStrike": false,
            "type": {
              "code": "SI",
              "description": "Sinker"
            }
          },
          "pitchData": {
            "startSpeed": 90.0,
            "breaks": {
              "spinRate": 1957
            }
          }
        },
        {
          "index": 12,
          "count": {
            "balls": 1,
            "strikes": 0
          },
          "details": {
            "code": "X",
            "description": "In play, Flyout",
            "isStrike": true,
            "type": {
              "code": "CU",
              "description": "Curveball"
            }
          },
          "pitchData": {
            "startSpeed": 79.6,
            "breaks": {
              "spinRate": 2851
            }
          },
          "hitData": {
            "launchSpeed": 91.7,
            "launchAngle": 27.5,
            "trajectory": "fly_ball"
          }
        }
      ],
      "runners": [
        {
          "movement": {
            "originBase": null,
            "start": null,
            "end": null,
            "outBase": "1B",
            "isOut": true,
            "outNumber": 2
          },
          "details": {
            "event": "Flyout",
            "eventType": "field_out",
            "movementReason": null,
            "runner": {
              "id": 545102,
              "fullName": "Marcus Thorne",
              "link": "/api/v1/people/545102"
            },
            "isScoringEvent": false,
            "rbi": false,
            "earned": false,
            "teamUnearned": false,
            "playIndex": 1
          },
          "credits": [
            {
              "player": {
                "id": 625202
              },
              "position": {
                "code": "8",
                "name": "Center Field",
                "abbreviation": "CF"
              },
              "credit": "putout"
            }
          ]
        }
      ]
    },
    {
      "result": {
        "type": "atBat",
        "event": "Double",
        "eventType": "double",
        "description": "",
        "rbi": 0,
        "awayScore": 0,
        "homeScore": 0
      },
      "about": {
        "atBatIndex": 5,
        "halfInning": "bottom",
        "isTopInning": false,
        "inning": 1,
        "isScoringPlay": false
      },
      "count": {
        "balls": 0,
        "strikes": 0,
        "outs": 2
      },
      "matchup": {
        "batter": {
          "id": 545103,
          "fullName": "Sam Decker",
          "link": "/api/v1/people/545103"
        },
        "batSide": {
          "code": "R",
          "description": "Right"
        },
        "pitcher": {
          "id": 645210,
          "fullName": "Miguel Garcia",
          "link": "/api/v1/people/645210"
        },
        "pitchHand": {
          "code": "L",
          "description": "Left"
        },
        "splits": {
          "batter": "vs_LHP",
          "pitcher": "vs_RHB",
          "menOnBase": "Empty"
        },
        "postOnSecond": {
          "id": 545103,
          "fullName": "Sam Decker",
          "link": "/api/v1/people/545103"
        }
      },
      "playEvents": [
        {
          "index": 13,
          "count": {
            "balls": 0,
            "strikes": 0
          },
          "details": {
            "code": "S",
            "description": "Swinging Strike",
            "isStrike": true,
            "type": {
              "code": "CU",
              "description": "Curveball"
            }
          },
          "pitchData": {
            "startSpeed": 79.1,
            "breaks": {
              "spinRate": 2998
            }
          }
        },
        {
          "index": 14,
          "count": {
            "balls": 0,
            "strikes": 1
          },
          "details": {
            "code": "B",
            "description": "Ball",
            "isStrike": false,
            "type": {
              "code": "SI",
              "description": "Sinker"
            }
          },
          "pitchData": {
            "startSpeed": 92.4,
            "breaks": {
              "spinRate": 2055
            }
          }
        },
        {
          "index": 15,
          "count": {
            "balls": 1,
            "strikes": 1
          },
          "details": {
            "code": "B",
            "description": "Ball",
            "isStrike": false,
            "type": {
              "code": "CU",
              "description": "Curveball"
            }
          },
          "pitchData": {
            "startSpeed": 79.9,
            "breaks": {
              "spinRate": 2916
            }
          }
        },
        {
          "index": 16,
          "count": {
            "balls": 2,
            "strikes": 1
          },
          "details": {
            "code": "X",
            "description": "In play, Double",
            "isStrike": true,
            "type": {
              "code": "SI",
              "description": "Sinker"
            }
          },
          "pitchData": {
            "startSpeed": 90.1
          },
          "hitData": {
            "launchSpeed": 109.5,
            "launchAngle": 10.6,
            "trajectory": "line_drive"
          }
        }
      ],
      "runners": [
        {
          "movement": {
            "originBase": null,
            "start": null,
            "end": "2B",
            "outBase": null,
            "isOut": false,
            "outNumber": null
          },
          "details": {
            "event": "Double",
            "eventType": "double",
            "movementReason": null,
            "runner": {
              "id": 545103,
              "fullName": "Sam Decker",
              "link": "/api/v1/people/545103"
            },
            "isScoringEvent": false,
            "rbi": false,
            "earned": false,
            "teamUnearned": false,
            "playIndex": 3
          },
          "credits": []
        }
      ]
    },
    {
      "result": {
        "type": "atBat",
        "event": "Strikeout",
        "eventType": "strikeout",
        "description": "",
        "rbi": 0,
        "awayScore": 0,
        "homeScore": 0
      },
      "about": {
        "atBatIndex": 6,
        "halfInning": "bottom",
        "isTopInning": false,
        "inning": 1,
        "isScoringPlay": false
      },
      "count": {
        "balls": 0,
        "strikes": 0,
        "outs": 3
      },
      "matchup": {
        "batter": {
          "id": 545104,
          "fullName": "Jackson Riley",
          "link": "/api/v1/people/545104"
        },
        "batSide": {
          "code": "R",
          "description": "Right"
        },
        "pitcher": {
          "id": 645210,
          "fullName": "Miguel Garcia",
          "link": "/api/v1/people/645210"
        },
        "pitchHand": {
          "code": "L",
          "description": "Left"
        },
        "splits": {
          "batter": "vs_LHP",
          "pitcher": "vs_RHB",
          "menOnBase": "RISP"
        },
        "postOnSecond": {
          "id": 545103,
          "fullName": "Sam Decker",
          "link": "/api/v1/people/545103"
        }
      },
      "playEvents": [
        {
          "index": 17,
          "count": {
            "balls": 0,
            "strikes": 0
          },
          "details": {
            "code": "S",
            "description": "Swinging Strike",
            "isStrike": true,
            "type": {
              "code": "CU",
              "description": "Curveball"
            }
          },
          "pitchData": {
            "startSpeed": 80.9,
            "breaks": {
              "spinRate": 2756
            }
          }
        },
        {
          "index": 18,
          "count": {
            "balls": 0,
            "strikes": 1
          },
          "details": {
            "code": "B",
            "description": "Ball",
            "isStrike": false,
            "type": {
              "code": "CU",
              "description": "Curveball"
            }
          },
          "pitchData": {
            "startSpeed": 80.7,
            "breaks": {
              "spinRate": 2769
            }
          }
        },
        {
          "index": 19,
          "count": {
            "balls": 1,
            "strikes": 1
          },
          "details": {
            "code": "S",
            "description": "Swinging Strike",
            "isStrike": true,
            "type": {
              "code": "CU",
              "description": "Curveball"
            }
          },
          "pitchData": {
            "startSpeed": 79.3,
            "breaks": {
              "spinRate": 2752
            }
          }
        },
        {
          "index": 20,
          "count": {
            "balls": 1,
            "strikes": 2
          },
          "details": {
            "code": "C",
            "description": "Called Strike",
            "isStrike": true,
            "type": {
              "code": "SI",
              "description": "Sinker"
            }
          },
          "pitchData": {
            "startSpeed": 90.9,
            "breaks": {
              "spinRate": 1962
            }
          }
        }
      ],
      "runners": [
        {
          "movement": {
            "originBase": null,
            "start": null,
            "end": null,
            "outBase": null,
            "isOut": true,
            "outNumber": 3
          },
          "details": {
            "event": "Strikeout",
            "eventType": "strikeout",
            "movementReason": null,
            "runner": {
              "id": 545104,
              "fullName": "Jackson Riley",
              "link": "/api/v1/people/545104"
            },
            "isScoringEvent": false,
            "rbi": false,
            "earned": false,
            "teamUnearned": false,
            "playIndex": 3
          },
          "credits": []
        }
      ]
    }
  ],
  "playCount": 77,
  "metadata": {
    "note": "This is a curated subset of plays for regression testing",
    "totalPlaysInGame": 77,
    "snapshotPlayCount": 6
  }
}